[
  {
    "id": 1,
    "user": {
      "id": 5,
      "name": "User 5",
      "email": "user5@example.com",
      "address_id": 5
    },
    "address_id": 5,
    "status": 1,
    "total_price": 1760189,
    "created_at": "2025-08-13 05:04:09.040601",
    "updated_at": "2025-08-15 05:04:09.040606",
    "items": [
      {
        "store_item_id": 5,
        "product_name": "Product 5",
        "quantity": 3,
        "price": 362027,
        "total_price": 1086081
      },
      {
        "store_item_id": 20,
        "product_name": "Product 20",
        "quantity": 3,
        "price": 104967,
        "total_price": 314901
      },
      {
        "store_item_id": 20,
        "product_name": "Product 20",
        "quantity": 1,
        "price": 104967,
        "total_price": 104967
      },
      {
        "store_item_id": 4,
        "product_name": "Product 4",
        "quantity": 4,
        "price": 63560,
        "total_price": 254240
      }
    ],
    "payment": {
      "transaction_id": "TX-1-3297",
      "reference_id": "REF-1-8990",
      "card_pan": "603799******5018",
      "amount": 1760189,
      "fee": 17601.89,
      "status": 4,
      "created_at": "2025-07-27 05:04:09.040580",
      "updated_at": "2025-08-15 05:04:09.040596"
    }
  },
  {
    "id": 2,
    "user": {
      "id": 5,
      "name": "User 5",
      "email": "user5@example.com",
      "address_id": 5
    },
    "address_id": 5,
    "status": 3,
    "total_price": 130452,
    "created_at": "2025-07-28 05:04:09.040633",
    "updated_at": "2025-08-15 05:04:09.040637",
    "items": [
      {
        "store_item_id": 16,
        "product_name": "Product 16",
        "quantity": 4,
        "price": 32613,
        "total_price": 130452
      }
    ],
    "payment": {
      "transaction_id": "TX-2-4167",
      "reference_id": "REF-2-8194",
      "card_pan": "603799******8178",
      "amount": 130452,
      "fee": 1304.52,
      "status": 1,
      "created_at": "2025-07-19 05:04:09.040625",
      "updated_at": "2025-08-15 05:04:09.040630"
    }
  },
  {
    "id": 3,
    "user": {
      "id": 4,
      "name": "User 4",
      "email": "user4@example.com",
      "address_id": 4
    },
    "address_id": 4,
    "status": 1,
    "total_price": 898212,
    "created_at": "2025-08-14 05:04:09.040660",
    "updated_at": "2025-08-15 05:04:09.040663",
    "items": [
      {
        "store_item_id": 7,
        "product_name": "Product 7",
        "quantity": 2,
        "price": 385546,
        "total_price": 771092
      },
      {
        "store_item_id": 4,
        "product_name": "Product 4",
        "quantity": 2,
        "price": 63560,
        "total_price": 127120
      }
    ],
    "payment": {
      "transaction_id": "TX-3-4015",
      "reference_id": "REF-3-7257",
      "card_pan": "603799******2860",
      "amount": 898212,
      "fee": 8982.12,
      "status": 1,
      "created_at": "2025-08-13 05:04:09.040653",
      "updated_at": "2025-08-15 05:04:09.040657"
    }
  },
  {
    "id": 4,
    "user": {
      "id": 1,
      "name": "User 1",
      "email": "user1@example.com",
      "address_id": 1
    },
    "address_id": 1,
    "status": 1,
    "total_price": 3858351,
    "created_at": "2025-07-17 05:04:09.040689",
    "updated_at": "2025-08-15 05:04:09.040693",
    "items": [
      {
        "store_item_id": 11,
        "product_name": "Product 11",
        "quantity": 1,
        "price": 282545,
        "total_price": 282545
      },
      {
        "store_item_id": 19,
        "product_name": "Product 19",
        "quantity": 5,
        "price": 273193,
        "total_price": 1365965
      },
      {
        "store_item_id": 18,
        "product_name": "Product 18",
        "quantity": 4,
        "price": 26070,
        "total_price": 104280
      },
      {
        "store_item_id": 7,
        "product_name": "Product 7",
        "quantity": 5,
        "price": 385546,
        "total_price": 1927730
      },
      {
        "store_item_id": 9,
        "product_name": "Product 9",
        "quantity": 1,
        "price": 177831,
        "total_price": 177831
      }
    ],
    "payment": {
      "transaction_id": "TX-4-3516",
      "reference_id": "REF-4-1126",
      "card_pan": "603799******8701",
      "amount": 3858351,
      "fee": 38583.51,
      "status": 4,
      "created_at": "2025-08-09 05:04:09.040683",
      "updated_at": "2025-08-15 05:04:09.040687"
    }
  },
  {
    "id": 5,
    "user": {
      "id": 5,
      "name": "User 5",
      "email": "user5@example.com",
      "address_id": 5
    },
    "address_id": 5,
    "status": 3,
    "total_price": 340386,
    "created_at": "2025-07-26 05:04:09.040711",
    "updated_at": "2025-08-15 05:04:09.040714",
    "items": [
      {
        "store_item_id": 20,
        "product_name": "Product 20",
        "quantity": 2,
        "price": 104967,
        "total_price": 209934
      },
      {
        "store_item_id": 16,
        "product_name": "Product 16",
        "quantity": 4,
        "price": 32613,
        "total_price": 130452
      }
    ],
    "payment": {
      "transaction_id": "TX-5-4045",
      "reference_id": "REF-5-7326",
      "card_pan": "603799******9297",
      "amount": 340386,
      "fee": 3403.86,
      "status": 4,
      "created_at": "2025-08-11 05:04:09.040705",
      "updated_at": "2025-08-15 05:04:09.040708"
    }
  },
  {
    "id": 6,
    "user": {
      "id": 4,
      "name": "User 4",
      "email": "user4@example.com",
      "address_id": 4
    },
    "address_id": 4,
    "status": 2,
    "total_price": 771092,
    "created_at": "2025-08-08 05:04:09.040749",
    "updated_at": "2025-08-15 05:04:09.040756",
    "items": [
      {
        "store_item_id": 7,
        "product_name": "Product 7",
        "quantity": 1,
        "price": 385546,
        "total_price": 385546
      },
      {
        "store_item_id": 7,
        "product_name": "Product 7",
        "quantity": 1,
        "price": 385546,
        "total_price": 385546
      }
    ],
    "payment": {
      "transaction_id": "TX-6-6519",
      "reference_id": "REF-6-7600",
      "card_pan": "603799******2074",
      "amount": 771092,
      "fee": 7710.92,
      "status": 3,
      "created_at": "2025-08-13 05:04:09.040736",
      "updated_at": "2025-08-15 05:04:09.040743"
    }
  },
  {
    "id": 7,
    "user": {
      "id": 1,
      "name": "User 1",
      "email": "user1@example.com",
      "address_id": 1
    },
    "address_id": 1,
    "status": 2,
    "total_price": 2183058,
    "created_at": "2025-08-03 05:04:09.040812",
    "updated_at": "2025-08-15 05:04:09.040819",
    "items": [
      {
        "store_item_id": 1,
        "product_name": "Product 1",
        "quantity": 1,
        "price": 443167,
        "total_price": 443167
      },
      {
        "store_item_id": 10,
        "product_name": "Product 10",
        "quantity": 3,
        "price": 287434,
        "total_price": 862302
      },
      {
        "store_item_id": 2,
        "product_name": "Product 2",
        "quantity": 3,
        "price": 70167,
        "total_price": 210501
      },
      {
        "store_item_id": 12,
        "product_name": "Product 12",
        "quantity": 2,
        "price": 209433,
        "total_price": 418866
      },
      {
        "store_item_id": 8,
        "product_name": "Product 8",
        "quantity": 2,
        "price": 124111,
        "total_price": 248222
      }
    ],
    "payment": {
      "transaction_id": "TX-7-9085",
      "reference_id": "REF-7-7334",
      "card_pan": "603799******1372",
      "amount": 2183058,
      "fee": 21830.58,
      "status": 2,
      "created_at": "2025-08-09 05:04:09.040799",
      "updated_at": "2025-08-15 05:04:09.040807"
    }
  },
  {
    "id": 8,
    "user": {
      "id": 1,
      "name": "User 1",
      "email": "user1@example.com",
      "address_id": 1
    },
    "address_id": 1,
    "status": 5,
    "total_price": 3700329,
    "created_at": "2025-07-20 05:04:09.040855",
    "updated_at": "2025-08-15 05:04:09.040861",
    "items": [
      {
        "store_item_id": 5,
        "product_name": "Product 5",
        "quantity": 5,
        "price": 362027,
        "total_price": 1810135
      },
      {
        "store_item_id": 16,
        "product_name": "Product 16",
        "quantity": 3,
        "price": 32613,
        "total_price": 97839
      },
      {
        "store_item_id": 6,
        "product_name": "Product 6",
        "quantity": 5,
        "price": 358471,
        "total_price": 1792355
      }
    ],
    "payment": {
      "transaction_id": "TX-8-6350",
      "reference_id": "REF-8-8941",
      "card_pan": "603799******9515",
      "amount": 3700329,
      "fee": 37003.29,
      "status": 4,
      "created_at": "2025-07-31 05:04:09.040845",
      "updated_at": "2025-08-15 05:04:09.040851"
    }
  },
  {
    "id": 9,
    "user": {
      "id": 4,
      "name": "User 4",
      "email": "user4@example.com",
      "address_id": 4
    },
    "address_id": 4,
    "status": 3,
    "total_price": 3119705,
    "created_at": "2025-07-29 05:04:09.040893",
    "updated_at": "2025-08-15 05:04:09.040898",
    "items": [
      {
        "store_item_id": 17,
        "product_name": "Product 17",
        "quantity": 2,
        "price": 451935,
        "total_price": 903870
      },
      {
        "store_item_id": 1,
        "product_name": "Product 1",
        "quantity": 5,
        "price": 443167,
        "total_price": 2215835
      }
    ],
    "payment": {
      "transaction_id": "TX-9-3498",
      "reference_id": "REF-9-9083",
      "card_pan": "603799******4901",
      "amount": 3119705,
      "fee": 31197.05,
      "status": 2,
      "created_at": "2025-07-29 05:04:09.040883",
      "updated_at": "2025-08-15 05:04:09.040888"
    }
  },
  {
    "id": 10,
    "user": {
      "id": 3,
      "name": "User 3",
      "email": "user3@example.com",
      "address_id": 3
    },
    "address_id": 3,
    "status": 1,
    "total_price": 78210,
    "created_at": "2025-08-07 05:04:09.040928",
    "updated_at": "2025-08-15 05:04:09.040934",
    "items": [
      {
        "store_item_id": 18,
        "product_name": "Product 18",
        "quantity": 3,
        "price": 26070,
        "total_price": 78210
      }
    ],
    "payment": {
      "transaction_id": "TX-10-3000",
      "reference_id": "REF-10-2387",
      "card_pan": "603799******6511",
      "amount": 78210,
      "fee": 782.1,
      "status": 4,
      "created_at": "2025-07-17 05:04:09.040917",
      "updated_at": "2025-08-15 05:04:09.040923"
    }
  },
  {
    "id": 11,
    "user": {
      "id": 3,
      "name": "User 3",
      "email": "user3@example.com",
      "address_id": 3
    },
    "address_id": 3,
    "status": 2,
    "total_price": 280668,
    "created_at": "2025-07-26 05:04:09.040963",
    "updated_at": "2025-08-15 05:04:09.040970",
    "items": [
      {
        "store_item_id": 2,
        "product_name": "Product 2",
        "quantity": 4,
        "price": 70167,
        "total_price": 280668
      }
    ],
    "payment": {
      "transaction_id": "TX-11-7831",
      "reference_id": "REF-11-3409",
      "card_pan": "603799******6795",
      "amount": 280668,
      "fee": 2806.68,
      "status": 4,
      "created_at": "2025-08-15 05:04:09.040951",
      "updated_at": "2025-08-15 05:04:09.040958"
    }
  },
  {
    "id": 12,
    "user": {
      "id": 2,
      "name": "User 2",
      "email": "user2@example.com",
      "address_id": 2
    },
    "address_id": 2,
    "status": 3,
    "total_price": 1130180,
    "created_at": "2025-08-09 05:04:09.041003",
    "updated_at": "2025-08-15 05:04:09.041009",
    "items": [
      {
        "store_item_id": 11,
        "product_name": "Product 11",
        "quantity": 4,
        "price": 282545,
        "total_price": 1130180
      }
    ],
    "payment": {
      "transaction_id": "TX-12-1738",
      "reference_id": "REF-12-3083",
      "card_pan": "603799******2751",
      "amount": 1130180,
      "fee": 11301.8,
      "status": 4,
      "created_at": "2025-07-16 05:04:09.040991",
      "updated_at": "2025-08-15 05:04:09.040997"
    }
  },
  {
    "id": 13,
    "user": {
      "id": 5,
      "name": "User 5",
      "email": "user5@example.com",
      "address_id": 5
    },
    "address_id": 5,
    "status": 2,
    "total_price": 2806099,
    "created_at": "2025-08-04 05:04:09.041048",
    "updated_at": "2025-08-15 05:04:09.041054",
    "items": [
      {
        "store_item_id": 19,
        "product_name": "Product 19",
        "quantity": 4,
        "price": 273193,
        "total_price": 1092772
      },
      {
        "store_item_id": 19,
        "product_name": "Product 19",
        "quantity": 4,
        "price": 273193,
        "total_price": 1092772
      },
      {
        "store_item_id": 8,
        "product_name": "Product 8",
        "quantity": 5,
        "price": 124111,
        "total_price": 620555
      }
    ],
    "payment": {
      "transaction_id": "TX-13-3051",
      "reference_id": "REF-13-2323",
      "card_pan": "603799******8769",
      "amount": 2806099,
      "fee": 28060.99,
      "status": 1,
      "created_at": "2025-07-28 05:04:09.041037",
      "updated_at": "2025-08-15 05:04:09.041043"
    }
  },
  {
    "id": 14,
    "user": {
      "id": 2,
      "name": "User 2",
      "email": "user2@example.com",
      "address_id": 2
    },
    "address_id": 2,
    "status": 1,
    "total_price": 2661445,
    "created_at": "2025-08-06 05:04:09.041089",
    "updated_at": "2025-08-15 05:04:09.041095",
    "items": [
      {
        "store_item_id": 11,
        "product_name": "Product 11",
        "quantity": 1,
        "price": 282545,
        "total_price": 282545
      },
      {
        "store_item_id": 1,
        "product_name": "Product 1",
        "quantity": 5,
        "price": 443167,
        "total_price": 2215835
      },
      {
        "store_item_id": 16,
        "product_name": "Product 16",
        "quantity": 5,
        "price": 32613,
        "total_price": 163065
      }
    ],
    "payment": {
      "transaction_id": "TX-14-2126",
      "reference_id": "REF-14-1495",
      "card_pan": "603799******8710",
      "amount": 2661445,
      "fee": 26614.45,
      "status": 3,
      "created_at": "2025-08-12 05:04:09.041079",
      "updated_at": "2025-08-15 05:04:09.041085"
    }
  },
  {
    "id": 15,
    "user": {
      "id": 4,
      "name": "User 4",
      "email": "user4@example.com",
      "address_id": 4
    },
    "address_id": 4,
    "status": 1,
    "total_price": 4407441,
    "created_at": "2025-08-14 05:04:09.041142",
    "updated_at": "2025-08-15 05:04:09.041148",
    "items": [
      {
        "store_item_id": 11,
        "product_name": "Product 11",
        "quantity": 4,
        "price": 282545,
        "total_price": 1130180
      },
      {
        "store_item_id": 7,
        "product_name": "Product 7",
        "quantity": 5,
        "price": 385546,
        "total_price": 1927730
      },
      {
        "store_item_id": 11,
        "product_name": "Product 11",
        "quantity": 1,
        "price": 282545,
        "total_price": 282545
      },
      {
        "store_item_id": 9,
        "product_name": "Product 9",
        "quantity": 4,
        "price": 177831,
        "total_price": 711324
      },
      {
        "store_item_id": 9,
        "product_name": "Product 9",
        "quantity": 2,
        "price": 177831,
        "total_price": 355662
      }
    ],
    "payment": {
      "transaction_id": "TX-15-8334",
      "reference_id": "REF-15-2737",
      "card_pan": "603799******6348",
      "amount": 4407441,
      "fee": 44074.41,
      "status": 3,
      "created_at": "2025-08-02 05:04:09.041129",
      "updated_at": "2025-08-15 05:04:09.041137"
    }
  },
  {
    "id": 16,
    "user": {
      "id": 4,
      "name": "User 4",
      "email": "user4@example.com",
      "address_id": 4
    },
    "address_id": 4,
    "status": 5,
    "total_price": 442021,
    "created_at": "2025-07-28 05:04:09.041193",
    "updated_at": "2025-08-15 05:04:09.041199",
    "items": [
      {
        "store_item_id": 4,
        "product_name": "Product 4",
        "quantity": 2,
        "price": 63560,
        "total_price": 127120
      },
      {
        "store_item_id": 20,
        "product_name": "Product 20",
        "quantity": 3,
        "price": 104967,
        "total_price": 314901
      }
    ],
    "payment": {
      "transaction_id": "TX-16-5566",
      "reference_id": "REF-16-6767",
      "card_pan": "603799******3658",
      "amount": 442021,
      "fee": 4420.21,
      "status": 4,
      "created_at": "2025-07-28 05:04:09.041182",
      "updated_at": "2025-08-15 05:04:09.041187"
    }
  },
  {
    "id": 17,
    "user": {
      "id": 5,
      "name": "User 5",
      "email": "user5@example.com",
      "address_id": 5
    },
    "address_id": 5,
    "status": 2,
    "total_price": 4993668,
    "created_at": "2025-08-11 05:04:09.041241",
    "updated_at": "2025-08-15 05:04:09.041246",
    "items": [
      {
        "store_item_id": 13,
        "product_name": "Product 13",
        "quantity": 5,
        "price": 219395,
        "total_price": 1096975
      },
      {
        "store_item_id": 12,
        "product_name": "Product 12",
        "quantity": 4,
        "price": 209433,
        "total_price": 837732
      },
      {
        "store_item_id": 17,
        "product_name": "Product 17",
        "quantity": 3,
        "price": 451935,
        "total_price": 1355805
      },
      {
        "store_item_id": 14,
        "product_name": "Product 14",
        "quantity": 4,
        "price": 292419,
        "total_price": 1169676
      },
      {
        "store_item_id": 15,
        "product_name": "Product 15",
        "quantity": 5,
        "price": 106696,
        "total_price": 533480
      }
    ],
    "payment": {
      "transaction_id": "TX-17-5215",
      "reference_id": "REF-17-1479",
      "card_pan": "603799******2558",
      "amount": 4993668,
      "fee": 49936.68,
      "status": 1,
      "created_at": "2025-07-21 05:04:09.041231",
      "updated_at": "2025-08-15 05:04:09.041236"
    }
  },
  {
    "id": 18,
    "user": {
      "id": 3,
      "name": "User 3",
      "email": "user3@example.com",
      "address_id": 3
    },
    "address_id": 3,
    "status": 2,
    "total_price": 5161569,
    "created_at": "2025-08-06 05:04:09.041310",
    "updated_at": "2025-08-15 05:04:09.041317",
    "items": [
      {
        "store_item_id": 17,
        "product_name": "Product 17",
        "quantity": 4,
        "price": 451935,
        "total_price": 1807740
      },
      {
        "store_item_id": 6,
        "product_name": "Product 6",
        "quantity": 5,
        "price": 358471,
        "total_price": 1792355
      },
      {
        "store_item_id": 8,
        "product_name": "Product 8",
        "quantity": 1,
        "price": 124111,
        "total_price": 124111
      },
      {
        "store_item_id": 17,
        "product_name": "Product 17",
        "quantity": 2,
        "price": 451935,
        "total_price": 903870
      },
      {
        "store_item_id": 9,
        "product_name": "Product 9",
        "quantity": 3,
        "price": 177831,
        "total_price": 533493
      }
    ],
    "payment": {
      "transaction_id": "TX-18-7804",
      "reference_id": "REF-18-7510",
      "card_pan": "603799******2959",
      "amount": 5161569,
      "fee": 51615.69,
      "status": 2,
      "created_at": "2025-08-14 05:04:09.041296",
      "updated_at": "2025-08-15 05:04:09.041305"
    }
  },
  {
    "id": 19,
    "user": {
      "id": 5,
      "name": "User 5",
      "email": "user5@example.com",
      "address_id": 5
    },
    "address_id": 5,
    "status": 3,
    "total_price": 1436098,
    "created_at": "2025-07-27 05:04:09.041363",
    "updated_at": "2025-08-15 05:04:09.041369",
    "items": [
      {
        "store_item_id": 3,
        "product_name": "Product 3",
        "quantity": 1,
        "price": 229992,
        "total_price": 229992
      },
      {
        "store_item_id": 11,
        "product_name": "Product 11",
        "quantity": 3,
        "price": 282545,
        "total_price": 847635
      },
      {
        "store_item_id": 6,
        "product_name": "Product 6",
        "quantity": 1,
        "price": 358471,
        "total_price": 358471
      }
    ],
    "payment": {
      "transaction_id": "TX-19-1998",
      "reference_id": "REF-19-2793",
      "card_pan": "603799******5469",
      "amount": 1436098,
      "fee": 14360.98,
      "status": 2,
      "created_at": "2025-08-09 05:04:09.041347",
      "updated_at": "2025-08-15 05:04:09.041358"
    }
  },
  {
    "id": 20,
    "user": {
      "id": 3,
      "name": "User 3",
      "email": "user3@example.com",
      "address_id": 3
    },
    "address_id": 3,
    "status": 4,
    "total_price": 4332698,
    "created_at": "2025-08-04 05:04:09.041410",
    "updated_at": "2025-08-15 05:04:09.041416",
    "items": [
      {
        "store_item_id": 6,
        "product_name": "Product 6",
        "quantity": 5,
        "price": 358471,
        "total_price": 1792355
      },
      {
        "store_item_id": 17,
        "product_name": "Product 17",
        "quantity": 5,
        "price": 451935,
        "total_price": 2259675
      },
      {
        "store_item_id": 2,
        "product_name": "Product 2",
        "quantity": 4,
        "price": 70167,
        "total_price": 280668
      }
    ],
    "payment": {
      "transaction_id": "TX-20-1513",
      "reference_id": "REF-20-4306",
      "card_pan": "603799******6750",
      "amount": 4332698,
      "fee": 43326.98,
      "status": 3,
      "created_at": "2025-07-28 05:04:09.041396",
      "updated_at": "2025-08-15 05:04:09.041404"
    }
  }
]